advdbg/__init__.py
advdbg/analyze.py
advdbg/colors.py
advdbg/core.py
advdbg/exceptions.py
advdbg/update.py
advdbg-0.3.1.dist-info/licenses/LICENSE
advdbg-0.3.1.dist-info/METADATA
advdbg-0.3.1.dist-info/WHEEL
advdbg-0.3.1.dist-info/top_level.txt
advdbg-0.3.1.dist-info/RECORD
