Metadata-Version: 2.4
Name: advdbg
Version: 0.3.1
Summary: Minimalist colorful debug logger
Author-email: Darkey <weplayok3@gmail.com>, WinFun <placeholder@gmail.com>
License: MIT
Keywords: debug,logger,debugging,color,terminal
Classifier: Programming Language :: Python :: 3
Classifier: License :: OSI Approved :: MIT License
Classifier: Operating System :: OS Independent
Requires-Python: >=3.6
License-File: LICENSE
Dynamic: license-file
